[
    {
        "id": "749efa89-d429-4a4e-8295-6ae9e01226d4",
        "Top": true,
        "note": "粤语港剧社区平台",
        "GEO": "Only-China",
        "Search": true,
        "title": "埋堆堆",
        "name": "SyncnextMDD",
        "api": "Syncnext://MDD"
    },
    {
        "id": "4671fc87-2542-4126-af71-a4af684039f8",
        "Top": true,
        "note": "片源高畫質追求",
        "Search": true,
        "title": "低端視頻",
        "name": "SyncnextDDRK",
        "api": "Syncnext://DDRK"
    },
    {
        "id": "67bf155c-e1f6-40ef-a474-417d55a740a5",
        "Top": true,
        "note": "海外剧、综艺、动漫",
        "Search": true,
        "title": "廠長資源",
        "name": "SyncnextCZSPP",
        "api": "Syncnext://CZSPP"
    },
    {
        "id": "7e3cb2a3-8a84-4dc9-8ba7-8d9a0071aee1",
        "Top": true,
        "note": "海量動漫",
        "Search": true,
        "title": "AGE 動漫",
        "name": "SyncnextAGE",
        "api": "Syncnext://AGE"
    },
    {
        "id": "759169a2-2287-484a-b835-1cf120d6c3b5",
        "Top": true,
        "note": "海外 IP",
        "Search": true,
        "title": "歐樂影院",
        "name": "SyncnextOLE",
        "api": "Syncnext://OLE"
    },
    {
        "id": "eb4706e0-824a-4acc-98a6-974a36170314",
        "Top": false,
        "note": "1080P 4M，限制搜索",
        "Search": false,
        "name": "快看资源",
        "Cover": "https://i.ibb.co/qFfYpvB/0-46909073898760023.png",
        "api": "https://kuaikan-api.com/api.php/provide/vod/from/kuaikan/at/xml"
    },
    {
        "id": "16fff133-fbf9-4871-becb-83e4efa2f53c",
        "Top": true,
        "note": "海外 IP，插入式廣告",
        "GEO": "Non-China",
        "Search": true,
        "name": "海外看資源",
        "ADBlockModel": "haiwaikan_v5",
        "api": "https://haiwaikan.com/api.php/provide/vod/at/xml "
    },
    {
        "id": "b70ab3a8-3e84-43a2-9c09-9334129a740d",
        "Top": true,
        "note": "無貼片，插入式廣告",
        "GEO": "Only-China",
        "Search": true,
        "name": "量子資源",
        "api": "https://cj.lziapi.com/api.php/provide/vod/from/lzm3u8/at/xml/"
    },
    {
        "id": "63915be4-a346-4b9b-89b5-404d030f4dfe",
        "Top": true,
        "note": "1080P 2.5M，插入式廣告",
        "GEO": "Only-China",
        "Search": true,
        "name": "非凡资源",
        "api": "http://new.ffzyapi8.com/api.php/provide/vod/from/ffm3u8/at/xml/"
    },
    {
        "id": "04e85a97-086f-4798-8cef-fd5ccefd7fc8",
        "Top": false,
        "note": "CC 版權電影",
        "name": "開放電影",
        "api": "https://vod-demo.onrender.com/pubdovod.php"
    },
    {
        "id": "91abf88c-ab75-4cf4-a3d0-f04c32af3ee1",
        "Top": false,
        "note": "有貼片",
        "Search": true,
        "name": "紅牛資源",
        "api": "https://www.hongniuzy2.com/api.php/provide/vod/from/hnm3u8/at/xml"
    },
    {
        "id": "373839b6-c04b-409d-8aae-813064d76b51",
        "note": "匹配海外看和量子",
        "Search": true,
        "name": "唐人街",
        "api": "https://www.tangrenjie.tv/api.php/provide/vod/at/xml"
    },
    {
        "id": "d0bb40b9-255a-4a46-ac59-fd6f0ab5d756",
        "note": "720P 文字貼片 1.25M",
        "Search": true,
        "name": "快车资源",
        "api": "https://caiji.kczyapi.com/api.php/provide/vod/from/kcm3u8/at/xml "
    },
    {
        "id": "45109de6-b970-4883-ac47-520bf868874d",
        "note": "720P 文字貼片 1M",
        "Search": true,
        "name": "金鹰资源",
        "api": "https://jyzyapi.com/provide/vod/from/jinyingm3u8/at/xml"
    },
    {
        "id": "61fea163-cf79-4c86-9c87-ba995d85aba1",
        "note": "720P 文字貼片 1.8M",
        "Search": true,
        "name": "光速资源",
        "api": "https://api.guangsuapi.com/api.php/provide/vod/from/gsm3u8/at/xml"
    },
    {
        "id": "1b8ffce4-daf3-4c71-9591-1427c28cac88",
        "note": "720P 文字貼片 0.85M",
        "Search": true,
        "name": "U酷资源",
        "api": "https://api.ukuapi.com/api.php/provide/vod/from/ukm3u8/at/xml"
    },
    {
        "id": "96000fba-e1f6-4144-8189-e95351629dd0",
        "note": "720P 貼片，不支持搜尋",
        "Search": false,
        "name": "百度资源",
        "api": "https://api.apibdzy.com/api.php/provide/vod/from/dbm3u8/at/xml/"
    },
    {
        "id": "21da9bf6-14da-4d1c-840a-1a9da109883f",
        "Search": true,
        "name": "新浪资源",
        "api": "https://api.xinlangapi.com/xinlangapi.php/provide/vod/from/xlm3u8/at/xml/"
    },
    {
        "id": "3afb7890-9dc7-497c-9b7c-fd162eb76cad",
        "note": "1080P，文字貼片",
        "Search": true,
        "name": "飞速资源",
        "api": "https://www.feisuzyapi.com/api.php/provide/vod/from/fsm3u8/at/xml/"
    },
    {
        "id": "bcf11cb4-8b9c-4a6a-a62d-c99796bfffb4",
        "note": "720P，大陸IP",
        "GEO": "Only-China",
        "Search": true,
        "name": "暴风资源",
        "api": "https://bfzyapi.com/api.php/provide/vod/at/xml/"
    },
    {
        "id": "1e72459c-3b38-4cbc-90e4-b7176b8fae66",
        "note": "1080P 1.5M，文字貼片",
        "Search": true,
        "name": "魔都资源",
        "api": "https://www.moduzy.com/api.php/provide/vod/at/xml/"
    },
    {
        "id": "c2e61e9b-9e5b-4a1d-83f0-766b2991128b",
        "note": "720P，1.5M",
        "Search": true,
        "name": "最大资源",
        "api": "https://api.zuidapi.com/api.php/provide/vod/from/zuidam3u8/at/xml/"
    },
    {
        "id": "27c7d34e-d7da-400f-b213-fc27b573b9e5",
        "note": "1080P，2M，文字貼片",
        "Search": true,
        "Line": "M3U8kuake",
        "name": "夸克资源",
        "api": "http://kuakezy1.com/api.php/provide/vod/from/M3U8kuake/at/xml/"
    },
    {
        "id": "89920f8d-7535-44d4-963c-b0c974367624",
        "Top": true,
        "note": "1080P，1M",
        "Search": true,
        "name": "索尼资源网",
        "api": "https://suoniapi.com/api.php/provide/vod/from/snm3u8/at/xml/"
    },
    {
        "id": "7bcd974b-5b1e-41c2-ab35-87129d2e6fe3",
        "note": "1080P，1.5M，不支持搜尋",
        "name": "高清资源库网",
        "api": "https://api.1080zyku.com/inc/api.php"
    },
    {
        "id": "d83e9e07-8e75-4b27-a081-5a24239c9d6a",
        "note": "非凡資源的鏡像源",
        "Search": true,
        "name": "映迷",
        "api": "https://www.inmi.app/api.php/provide/vod/at/xml/"
    },
    {
        "id": "9268d65f-411c-48f9-92be-157503334bba",
        "note": "720P，貼片廣告",
        "Search": true,
        "name": "快车资源",
        "api": "https://caiji.kczyapi.com/api.php/provide/vod/from/kcm3u8/at/xml"
    },
    {
        "id": "d8432d7d-d5ca-4030-862e-21e656909fa9",
        "note": "1080P，1.5M",
        "Search": true,
        "name": "闪电资源",
        "api": "http://sdzyapi.com/api.php/provide/vod/at/xml/"
    },
    {
        "id": "faa43804-70f1-410e-8855-395792e5f426",
        "Search": true,
        "name": "虎牙資源",
        "api": "https://www.huyaapi.com/api.php/provide/vod/from/hym3u8/at/xml/"
    },
    {
        "id": "89a8ae52-b131-40e6-ba04-7554cf3c7325",
        "note": "720P，無廣告。OneDrive 網盤地址。",
        "Search": true,
        "name": "粵語劇",
        "api": "syncnextPlugin://https://raw.githubusercontent.com/qoli/syncnextPlugin/main/plugin_colafun/config.json"
    },
    {
        "id": "fdd8c199-1ce6-4d97-848f-8d1952211cb8",
        "Top": true,
        "note": "1080P，官網標無廣告，量子鏡像",
        "Search": true,
        "name": "天翼资源",
        "api": "https://www.911ysw.top/tianyi.php/provide/vod/from/lzm3u8/at/xml/"
    }
]